{
    "manifest": {
        "author": "Rhy#1752",
        "name": "DD Gold Redux Addon",
        "version": "1.4.1",
        "license": "MIT",
        "updater": "https:\/\/raw.githubusercontent.com\/RhyMegu\/DarkDiscordRedux\/main\/DDGOplus.json"
    },
    "background": {},
    "fonts": {},
    "simple_colors": {
        "active_channel": 1035508259
    },
    "colors": {
        "primary_dark_100": -993809589,
        "primary_dark_300": -4679133,
        "uikit_btn_bg_color_selector_green": -4679133
    },
    "drawable_tints": {
        "ic_pin_24dp": -3953845,
        "ic_thread": -4679133,
        "ic_sidebar_pins_on_dark_24dp": -4679133,
        "ic_sidebar_pins_off_dark_24dp": -8492779,
        "ic_sidebar_notifications_off_dark_24dp": -8492779,
        "ic_sidebar_notifications_on_dark_24dp": -4679133,
        "ic_channel_text": -4679133,
        "ic_mark_unread_24dp": -4679133,
        "ic_user_profile_action_message_white_a60_24dp": -4679133,
        "ic_user_profile_action_message_grey_a60_24dp": -8492779,
        "ic_chat_message_white_24dp": -4679133,
        "ic_channel_text_nsfw": -4679133,
        "ic_channel_text_locked": -4679133,
        "ic_channel_lock_16dp": -4679133,
        "ic_channel_announcements_thread_nsfw": -4679133,
        "ic_channel_announcements_thread_locked": -4679133,
        "ic_channel_announcements_thread": -4679133,
        "ic_channel_announcements_nsfw": -4679133,
        "ic_channel_announcements_16dp": -4679133,
        "ic_channel_announcements_locked": -4679133,
        "ic_channel_announcements": -4679133,
        "ic_menu_24dp": -4679133,
        "ic_bell_16dp": -4679133,
        "ic_bell_12dp": -4679133,
        "ic_bell_20dp": -4679133,
        "ic_guild_invite_24dp": -4679133,
        "ic_settings_24dp": -4679133,
        "drawable_button_grey": -4679133
    },
    "raws": {}
}